timstools/__init__.py
timstools/timer.py
timstools/timstools.py
timstools/ui.py
timstools-0.1.4.dist-info/DESCRIPTION.rst
timstools-0.1.4.dist-info/METADATA
timstools-0.1.4.dist-info/RECORD
timstools-0.1.4.dist-info/WHEEL
timstools-0.1.4.dist-info/metadata.json
timstools-0.1.4.dist-info/top_level.txt
