Metadata-Version: 2.0
Name: timstools
Version: 0.1.4
Summary: Collection of tools for helping you program faster
Home-page: https://github.com/timeyyy/timstools
Author: tmothy eichler
Author-email: tim_eichler@hotmail.com
License: BSD3
Keywords: misc programming tools python3 general generic
Platform: UNKNOWN
Classifier: Development Status :: 3 - Alpha
Classifier: Intended Audience :: Developers
Classifier: Topic :: Software Development :: Build Tools
Classifier: License :: OSI Approved :: BSD License
Classifier: Programming Language :: Python :: 3.2
Classifier: Programming Language :: Python :: 3.3
Classifier: Programming Language :: Python :: 3.4
